myCalculatorPackage12/__init__.py
myCalculatorPackage12/division/__init__.py
myCalculatorPackage12/division/divide.py
myCalculatorPackage12/multiplication/__init__.py
myCalculatorPackage12/multiplication/multiply.py
myCalculatorPackage12-0.0.2.dist-info/LICENSE.txt
myCalculatorPackage12-0.0.2.dist-info/METADATA
myCalculatorPackage12-0.0.2.dist-info/WHEEL
myCalculatorPackage12-0.0.2.dist-info/top_level.txt
myCalculatorPackage12-0.0.2.dist-info/RECORD
